gcp_connector/__init__.py
gcp_connector/modulo.py
gcp_connector-0.1.7.dist-info/METADATA
gcp_connector-0.1.7.dist-info/WHEEL
gcp_connector-0.1.7.dist-info/top_level.txt
gcp_connector-0.1.7.dist-info/RECORD
